apeagent/ApeAgent.py
apeagent/__init__.py
apeagent-0.1.0.dist-info/METADATA
apeagent-0.1.0.dist-info/WHEEL
apeagent-0.1.0.dist-info/top_level.txt
apeagent-0.1.0.dist-info/RECORD
