Metadata-Version: 2.1
Name: apeagent
Version: 0.1.0
Summary: A simple framework to manage agents and tool-based functions
Home-page: https://github.com/tu_usuario/apeagent
Author: Macaque Consulting
Author-email: marc.riera@macaqueconsulting.com
Classifier: Programming Language :: Python :: 3.11
Classifier: License :: OSI Approved :: MIT License
Classifier: Operating System :: OS Independent
Requires-Python: >=3.11
Requires-Dist: openai ==1.53.0
